matflow_abaqus/__init__.py
matflow_abaqus/_version.py
matflow_abaqus/main.py
matflow_abaqus-0.1.2.dist-info/LICENSE
matflow_abaqus-0.1.2.dist-info/METADATA
matflow_abaqus-0.1.2.dist-info/WHEEL
matflow_abaqus-0.1.2.dist-info/entry_points.txt
matflow_abaqus-0.1.2.dist-info/top_level.txt
matflow_abaqus-0.1.2.dist-info/RECORD
