Metadata-Version: 2.1
Name: matflow-abaqus
Version: 0.1.2
Summary: Matflow extension for the FE code Abaqus.
Home-page: UNKNOWN
Author: Maria Yankova
Author-email: maria.yankova@manchester.ac.uk
License: MIT license
Project-URL: GitHub, https://github.com/maria-yankova/matflow-abaqus
Keywords: matflow,materials-science,computational-workflow
Platform: UNKNOWN
Classifier: Development Status :: 4 - Beta
Classifier: Intended Audience :: Science/Research
Classifier: Topic :: Scientific/Engineering
Classifier: Operating System :: OS Independent
Classifier: License :: OSI Approved :: MIT License
Classifier: Natural Language :: English
Classifier: Programming Language :: Python :: 3
Classifier: Programming Language :: Python :: 3.6
Classifier: Programming Language :: Python :: 3.7
Classifier: Programming Language :: Python :: 3.8
Requires-Python: >=3.6
Requires-Dist: matflow
